{"markups": {"effect": [], "precondition": ["lambda thinker: not thinker.occupation", "lambda thinker: thinker.dislikes(thinker.boss)", "lambda thinker: thinker.occupation", "lambda thinker: thinker.likes(thinker.boss)"], "symbol": ["boss 10", "job 10"]}, "nonterminals": {"exasperated interjection,": {"complete": true, "deep": true, "markup": {}, "rules": [{"app_rate": 1, "expansion": ["gosh,"]}, {"app_rate": 1, "expansion": ["jeez,"]}, {"app_rate": 4, "expansion": ["holy mackeral,"]}, {"app_rate": 1, "expansion": [" "]}]}, "intensifier": {"complete": true, "deep": false, "markup": {}, "rules": [{"app_rate": 1, "expansion": ["very"]}, {"app_rate": 1, "expansion": ["definitely"]}]}, "jerk / mean person / rude person": {"complete": true, "deep": false, "markup": {}, "rules": [{"app_rate": 1, "expansion": ["jerk"]}, {"app_rate": 1, "expansion": ["mean person"]}, {"app_rate": 1, "expansion": ["rude person"]}]}, "my boss / boss.first_name": {"complete": true, "deep": false, "markup": {}, "rules": [{"app_rate": 1, "expansion": ["my boss"]}, {"app_rate": 1, "expansion": ["[thinker.boss.first_name]"]}]}, "the worst / no fun / hardly worth showing up": {"complete": true, "deep": false, "markup": {}, "rules": [{"app_rate": 1, "expansion": ["the worst"]}, {"app_rate": 1, "expansion": ["no fun"]}, {"app_rate": 1, "expansion": ["hardly worth showing up"]}]}, "think about job in general": {"complete": true, "deep": true, "markup": {"precondition": ["lambda thinker: thinker.occupation"], "symbol": ["job 10"]}, "rules": [{"app_rate": 1, "expansion": ["i go to work a lot"]}]}, "think about job when i hate my boss": {"complete": true, "deep": true, "markup": {"precondition": ["lambda thinker: thinker.dislikes(thinker.boss)"], "symbol": ["boss 10", "job 10"]}, "rules": [{"app_rate": 1, "expansion": ["going to ", "[[work / my job / occupation.name]]", " is ", "[[the worst / no fun / hardly worth showing up]]", ", i hope ", "[[my boss / boss.first_name]]", " lightens up."]}, {"app_rate": 1, "expansion": ["work was so stressful the other day, ", "[[my boss / boss.first_name]]", " is ", "[[intensifier]]", " hard to work with"]}, {"app_rate": 1, "expansion": ["my boss is such a ", "[[jerk / mean person / rude person]]"]}, {"app_rate": 1, "expansion": ["[[exasperated interjection,]]", " my boss is such a ", "[[jerk / mean person / rude person]]"]}]}, "think about job when i like my boss": {"complete": true, "deep": true, "markup": {"precondition": ["lambda thinker: thinker.likes(thinker.boss)"], "symbol": ["boss 10", "job 10"]}, "rules": [{"app_rate": 1, "expansion": ["my boss is ", "[[intensifier]]", " great"]}]}, "think abut job when i have no job": {"complete": true, "deep": true, "markup": {"precondition": ["lambda thinker: not thinker.occupation"], "symbol": ["job 10"]}, "rules": [{"app_rate": 1, "expansion": ["i wonder if i should get another job soon"]}]}, "work / my job / occupation.name": {"complete": true, "deep": false, "markup": {}, "rules": [{"app_rate": 1, "expansion": ["work"]}, {"app_rate": 1, "expansion": ["my job"]}, {"app_rate": 1, "expansion": ["[thinker.occupation.name]"]}]}}, "system_vars": ["[intensifier]", "[thinker.boss.first_name]", "[thinker.occupation.name]"]}